dockershit/__init__.py
dockershit/command.py
dockershit/docker.py
dockershit/docker_file.py
dockershit/dockershit.py
dockershit/keyboard.py
dockershit-0.1.3.dist-info/entry_points.txt
dockershit-0.1.3.dist-info/licenses/LICENSE.md
dockershit-0.1.3.dist-info/WHEEL
dockershit-0.1.3.dist-info/METADATA
dockershit-0.1.3.dist-info/RECORD
