Metadata-Version: 2.4
Name: dockershit
Version: 0.1.3
Summary: dockerfile shell interactive terminal
Author-email: Gareth Davidson <gaz@bitplane.net>
Classifier: Development Status :: 3 - Alpha
Classifier: Environment :: Console
Classifier: Intended Audience :: Developers
Classifier: License :: Public Domain
Classifier: Programming Language :: Python :: 3
Classifier: Programming Language :: Python :: 3.11
Classifier: Topic :: System :: Installation/Setup
Classifier: Topic :: System :: Systems Administration
Classifier: Topic :: Utilities
License-File: LICENSE.md
Requires-Dist: flake8 ; extra == "dev"
Requires-Dist: build ; extra == "dev"
Requires-Dist: pre-commit ; extra == "dev"
Requires-Dist: pytest ; extra == "dev"
Requires-Dist: coverage ; extra == "dev"
Requires-Dist: pytest-cov ; extra == "dev"
Requires-Dist: twine ; extra == "dev"
Provides-Extra: dev
